[
    {
     "id": 1,
     "name": "Kevin",
     "age": 10,
     "job": "Tester"
   },
   {
     "id": 2,
     "name": "Tim",
     "age": 40,
     "job": "Developer"
   },
   {
     "id": 3,
     "name": "John",
     "age": 30,
     "job": "Writer"
   },
   {
     "id": 4,
     "name": "Thomas",
     "age": 30,
     "job": "Teacher"
   },
   {
    "id": 5,
    "name": "Chris",
    "age": 46,
    "job": "Principal"
  },
  {
    "id": 6,
    "name": "Elvia",
    "age": 38,
    "job": "Deliverman"
  },
  {
    "id": 7,
    "name": "Buckner",
    "age": 26,
    "job": "Principal"
  },
  {
    "id": 8,
    "name": "Shepherd",
    "age": 25,
    "job": "Janitor"
  },
  {
    "id": 9,
    "name": "Baxter",
    "age": 30,
    "job": "Lawyer"
  },
  {
    "id": 10,
    "name": "Louella",
    "age": 53,
    "job": "Janitor"
  },
  {
    "id": 11,
    "name": "Shelton",
    "age": 52,
    "job": "Lawyer"
  },
  {
    "id": 12,
    "name": "Mari",
    "age": 32,
    "job": "Writer"
  },
  {
    "id": 13,
    "name": "Craft",
    "age": 22,
    "job": "Writer"
  },
  {
    "id": 14,
    "name": "Hodges",
    "age": 32,
    "job": "Lawyer"
  },
  {
    "id": 15,
    "name": "Chandra",
    "age": 27,
    "job": "Writer"
  },
  {
    "id": 16,
    "name": "Laurel",
    "age": 35,
    "job": "Writer"
  },
  {
    "id": 17,
    "name": "Kinney",
    "age": 41,
    "job": "Teacher"
  },
  {
    "id": 18,
    "name": "Tim",
    "age": 35,
    "job": "Writer"
  },
  {
    "id": 19,
    "name": "Briana",
    "age": 58,
    "job": "Teacher"
  },
  {
    "id": 20,
    "name": "Strickland",
    "age": 50,
    "job": "Developer"
  }
 ]